fastybird_triggers_module/__init__.py
fastybird_triggers_module/bootstrap.py
fastybird_triggers_module/exceptions.py
fastybird_triggers_module/logger.py
fastybird_triggers_module/py.typed
fastybird_triggers_module/subscriber.py
fastybird_triggers_module/automation/__init__.py
fastybird_triggers_module/automation/automation.py
fastybird_triggers_module/automation/consumer.py
fastybird_triggers_module/automation/queue.py
fastybird_triggers_module/entities/__init__.py
fastybird_triggers_module/entities/action.py
fastybird_triggers_module/entities/base.py
fastybird_triggers_module/entities/condition.py
fastybird_triggers_module/entities/notification.py
fastybird_triggers_module/entities/trigger.py
fastybird_triggers_module/managers/__init__.py
fastybird_triggers_module/managers/action.py
fastybird_triggers_module/managers/base.py
fastybird_triggers_module/managers/condition.py
fastybird_triggers_module/managers/notification.py
fastybird_triggers_module/managers/state.py
fastybird_triggers_module/managers/trigger.py
fastybird_triggers_module/repositories/__init__.py
fastybird_triggers_module/repositories/action.py
fastybird_triggers_module/repositories/condition.py
fastybird_triggers_module/repositories/notification.py
fastybird_triggers_module/repositories/state.py
fastybird_triggers_module/repositories/trigger.py
fastybird_triggers_module/state/__init__.py
fastybird_triggers_module/state/action.py
fastybird_triggers_module/state/condition.py
tests/__init__.py
tests/pytests/__init__.py
tests/pytests/tests.py
tests/pytests/managers/__init__.py
tests/pytests/managers/test_actions.py
tests/pytests/managers/test_triggers.py
tests/pytests/repositories/__init__.py
tests/pytests/repositories/test_actions.py
tests/pytests/repositories/test_conditions.py
tests/pytests/repositories/test_notifications.py
tests/pytests/repositories/test_triggers.py
tests/pytests/repositories/test_triggers_controls.py
fastybird_triggers_module-0.46.0.dist-info/LICENSE.md
fastybird_triggers_module-0.46.0.dist-info/METADATA
fastybird_triggers_module-0.46.0.dist-info/WHEEL
fastybird_triggers_module-0.46.0.dist-info/top_level.txt
fastybird_triggers_module-0.46.0.dist-info/RECORD
